docs/sphinx_extensions/netket_citations.py
netket/__init__.py
netket/_version.py
netket/errors.py
netket/exact.py
netket/_src/driver/vmc_sr.py
netket/_src/ngd/kwargs.py
netket/_src/ngd/sr.py
netket/_src/ngd/sr_srt_common.py
netket/_src/ngd/srt.py
netket/_src/ngd/srt_onthefly.py
netket/_src/nn/apply_operator/functional.py
netket/_src/nn/apply_operator/linen.py
netket/_src/nn/apply_operator/nnx.py
netket/_src/operator/normal_order_utils.py
netket/_src/operator/pyscf_api.py
netket/_src/operator/pyscf_utils.py
netket/_src/operator/particle_number_conserving_fermionic/conversion.py
netket/_src/operator/particle_number_conserving_fermionic/fermihubbard.py
netket/_src/operator/particle_number_conserving_fermionic/kernels.py
netket/_src/operator/particle_number_conserving_fermionic/operator_data.py
netket/_src/operator/particle_number_conserving_fermionic/operators.py
netket/_src/operator/permutation/base.py
netket/_src/operator/permutation/construct.py
netket/_src/operator/permutation/fermion.py
netket/_src/operator/permutation/spin.py
netket/_src/operator/permutation/trace_utils.py
netket/_src/symmetry/canonical_representation.py
netket/_src/symmetry/representation.py
netket/_src/symmetry/representation_construction.py
netket/_src/vqs/transformed_vstate.py
netket/_src/vqs/fermion_mf/__init__.py
netket/_src/vqs/fermion_mf/expectation.py
netket/_src/vqs/fermion_mf/qgt.py
netket/_src/vqs/fermion_mf/state.py
netket/callbacks/__init__.py
netket/callbacks/convergence_stopping.py
netket/callbacks/early_stopping.py
netket/callbacks/invalid_loss_stopping.py
netket/callbacks/timeout.py
netket/driver/__init__.py
netket/driver/abstract_variational_driver.py
netket/driver/steady_state.py
netket/driver/vmc.py
netket/experimental/__init__.py
netket/experimental/driver/__init__.py
netket/experimental/driver/infidelity_sr.py
netket/experimental/driver/tdvp.py
netket/experimental/driver/tdvp_common.py
netket/experimental/driver/tdvp_schmitt.py
netket/experimental/dynamics/__init__.py
netket-3.21.0.dist-info/METADATA
netket-3.21.0.dist-info/WHEEL
netket-3.21.0.dist-info/entry_points.txt
netket-3.21.0.dist-info/licenses/LICENSE
netket-3.21.0.dist-info/RECORD
